df_autosk/__init__.py
df_autosk/df_autosk.py
df_autosk-0.0.4.dist-info/LICENSE
df_autosk-0.0.4.dist-info/METADATA
df_autosk-0.0.4.dist-info/WHEEL
df_autosk-0.0.4.dist-info/top_level.txt
df_autosk-0.0.4.dist-info/RECORD
