Metadata-Version: 2.1
Name: df-autosk
Version: 0.0.4
Summary: A CascadeForestClassifier extension of AutoSklearn classifier 
Author-email: Katarina Nocarova <469381@mail.muni.cz>
Project-URL: Homepage, https://gitlab.fi.muni.cz/xsvecova/deep-forest-and-after/-/tree/main/df_autosk
Classifier: Programming Language :: Python :: 3
Classifier: License :: OSI Approved :: MIT License
Classifier: Operating System :: OS Independent
Requires-Python: >=3.8
License-File: LICENSE
